{
    "id": 17795,
    "cast": [
        {
            "adult": false,
            "gender": 2,
            "id": 3151,
            "known_for_department": "Acting",
            "name": "Jack Lemmon",
            "original_name": "Jack Lemmon",
            "popularity": 10.019,
            "profile_path": "/yfS8K77QzICgOcBuQfd5WfgOnCo.jpg",
            "cast_id": 2,
            "character": "President Russell P. Kramer",
            "credit_id": "52fe47479251416c75093c4b",
            "order": 0
        },
        {
            "adult": false,
            "gender": 2,
            "id": 16896,
            "known_for_department": "Acting",
            "name": "James Garner",
            "original_name": "James Garner",
            "popularity": 10.471,
            "profile_path": "/hiPky3VwIOAlmPhJwzRovEsGDrI.jpg",
            "cast_id": 3,
            "character": "President Matt Douglas",
            "credit_id": "52fe47479251416c75093c4f",
            "order": 1
        },
        {
            "adult": false,
            "gender": 2,
            "id": 707,
            "known_for_department": "Acting",
            "name": "Dan Aykroyd",
            "original_name": "Dan Aykroyd",
            "popularity": 24.353,
            "profile_path": "/iVMmeVJx8IpCEjlGBZWzIWvX5Qo.jpg",
            "cast_id": 4,
            "character": "President William Haney",
            "credit_id": "52fe47479251416c75093c53",
            "order": 2
        },
        {
            "adult": false,
            "gender": 2,
            "id": 11512,
            "known_for_department": "Acting",
            "name": "John Heard",
            "original_name": "John Heard",
            "popularity": 18.229,
            "profile_path": "/zjhcxrCFK4q0C1gtVmeN8FeqCw0.jpg",
            "cast_id": 5,
            "character": "Vice President Ted Matthews",
            "credit_id": "52fe47489251416c75093c57",
            "order": 3
        },
        {
            "adult": false,
            "gender": 2,
            "id": 11065,
            "known_for_department": "Acting",
            "name": "Wilford Brimley",
            "original_name": "Wilford Brimley",
            "popularity": 11.276,
            "profile_path": "/pOfcXSGKiHcdFIcnhBV3ibGUruW.jpg",
            "cast_id": 6,
            "character": "Joe Hollis",
            "credit_id": "52fe47489251416c75093c5b",
            "order": 4
        },
        {
            "adult": false,
            "gender": 1,
            "id": 7570,
            "known_for_department": "Acting",
            "name": "Lauren Bacall",
            "original_name": "Lauren Bacall",
            "popularity": 7.341,
            "profile_path": "/iCOzbSzCSUC6D9EcyXtVb2FRNu0.jpg",
            "cast_id": 7,
            "character": "Margaret Kramer",
            "credit_id": "52fe47489251416c75093c5f",
            "order": 5
        },
        {
            "adult": false,
            "gender": 1,
            "id": 6068,
            "known_for_department": "Acting",
            "name": "Sela Ward",
            "original_name": "Sela Ward",
            "popularity": 15.518,
            "profile_path": "/pzQuH9vm182Ar2vpUsakKzxPNV7.jpg",
            "cast_id": 8,
            "character": "Kaye Griffin",
            "credit_id": "52fe47489251416c75093c63",
            "order": 6
        },
        {
            "adult": false,
            "gender": 2,
            "id": 11367,
            "known_for_department": "Acting",
            "name": "Bradley Whitford",
            "original_name": "Bradley Whitford",
            "popularity": 21.678,
            "profile_path": "/oeDv2qZWTxELLaNtOIoeG72leNY.jpg",
            "cast_id": 10,
            "character": "Carl Witnaur",
            "credit_id": "52fe47489251416c75093c67",
            "order": 7
        },
        {
            "adult": false,
            "gender": 2,
            "id": 5616,
            "known_for_department": "Acting",
            "name": "Everett McGill",
            "original_name": "Everett McGill",
            "popularity": 9.387,
            "profile_path": "/4LMEfVrkkifznxMtrQjDINJazts.jpg",
            "cast_id": 11,
            "character": "Col. Paul Tanner",
            "credit_id": "52fe47489251416c75093c6b",
            "order": 8
        },
        {
            "adult": false,
            "gender": 2,
            "id": 8986,
            "known_for_department": "Acting",
            "name": "James Rebhorn",
            "original_name": "James Rebhorn",
            "popularity": 8.852,
            "profile_path": "/jRdR3q28gTPQU6eWRgiIqzGuMKU.jpg",
            "cast_id": 17,
            "character": "Charlie Reynolds",
            "credit_id": "57f49e0ac3a3680542001c41",
            "order": 9
        },
        {
            "adult": false,
            "gender": 1,
            "id": 5700,
            "known_for_department": "Acting",
            "name": "Esther Rolle",
            "original_name": "Esther Rolle",
            "popularity": 2.993,
            "profile_path": "/qC1k4WhH9vULIKucdBbgfiQ5bmD.jpg",
            "cast_id": 18,
            "character": "Rita",
            "credit_id": "57f49e12c3a3680542001c46",
            "order": 10
        },
        {
            "adult": false,
            "gender": 2,
            "id": 1240,
            "known_for_department": "Acting",
            "name": "Jack Kehler",
            "original_name": "Jack Kehler",
            "popularity": 7.043,
            "profile_path": "/5vPBJw92OKtD5pNO0TTPZvvxooV.jpg",
            "cast_id": 19,
            "character": "Wayne",
            "credit_id": "57f49e1fc3a368053d00201c",
            "order": 11
        },
        {
            "adult": false,
            "gender": 1,
            "id": 35517,
            "known_for_department": "Acting",
            "name": "Connie Ray",
            "original_name": "Connie Ray",
            "popularity": 5.406,
            "profile_path": "/gvJIXnCrzLYFQ3ZSNd2I5vjehOm.jpg",
            "cast_id": 20,
            "character": "Genny",
            "credit_id": "57f49e26c3a368054e001ce5",
            "order": 12
        },
        {
            "adult": false,
            "gender": 2,
            "id": 140250,
            "known_for_department": "Acting",
            "name": "Tom Everett",
            "original_name": "Tom Everett",
            "popularity": 3.981,
            "profile_path": "/lJIlLkadJ62eRai5BRgmmyObeiC.jpg",
            "cast_id": 21,
            "character": "NSA Agent Wilkerson",
            "credit_id": "57f49e3c9251411c71002070",
            "order": 13
        },
        {
            "adult": false,
            "gender": 2,
            "id": 1470,
            "known_for_department": "Acting",
            "name": "Wayne Duvall",
            "original_name": "Wayne Duvall",
            "popularity": 14.567,
            "profile_path": "/lLCBQSWbxtl1oWK3pCS2oQff7Y9.jpg",
            "cast_id": 22,
            "character": "Chet",
            "credit_id": "57f49e4ac3a368055d001db8",
            "order": 14
        },
        {
            "adult": false,
            "gender": 2,
            "id": 454,
            "known_for_department": "Acting",
            "name": "Michael Pe\u00f1a",
            "original_name": "Michael Pe\u00f1a",
            "popularity": 19.989,
            "profile_path": "/tu5CtDtVP4oZBVQgi0s4vgZErIg.jpg",
            "cast_id": 23,
            "character": "Ernesto",
            "credit_id": "57f49e6cc3a368053d002045",
            "order": 15
        },
        {
            "adult": false,
            "gender": 2,
            "id": 53552,
            "known_for_department": "Acting",
            "name": "John O'Leary",
            "original_name": "John O'Leary",
            "popularity": 6.488,
            "profile_path": "/v73J1QaYPRobDRDIqJYRqCDx52V.jpg",
            "cast_id": 24,
            "character": "Ben, Caretaker",
            "credit_id": "57f49e7fc3a3680559002076",
            "order": 16
        },
        {
            "adult": false,
            "gender": 2,
            "id": 55270,
            "known_for_department": "Acting",
            "name": "Tom Wright",
            "original_name": "Tom Wright",
            "popularity": 6.788,
            "profile_path": "/3Jmwf493R4e9cis5689Nn0DLgqt.jpg",
            "cast_id": 26,
            "character": "Jim",
            "credit_id": "5ed3e1aeaaec71001f6e6ddd",
            "order": 17
        },
        {
            "adult": false,
            "gender": 2,
            "id": 122807,
            "known_for_department": "Acting",
            "name": "Dana Gould",
            "original_name": "Dana Gould",
            "popularity": 3.153,
            "profile_path": "/iNbx9rbjFTrnwdcl1bIdnLzLods.jpg",
            "cast_id": 27,
            "character": "Sandwich Guy at Book Convention",
            "credit_id": "5f7a4a71197de40038782d25",
            "order": 18
        }
    ],
    "crew": [
        {
            "adult": false,
            "gender": 2,
            "id": 3805,
            "known_for_department": "Production",
            "name": "Jon Peters",
            "original_name": "Jon Peters",
            "popularity": 1.166,
            "profile_path": "/ts4JBYG2LEbquRzExGHer1122AI.jpg",
            "credit_id": "5febb918d7107e003e276850",
            "department": "Production",
            "job": "Producer"
        },
        {
            "adult": false,
            "gender": 2,
            "id": 9967,
            "known_for_department": "Art",
            "name": "James D. Bissell",
            "original_name": "James D. Bissell",
            "popularity": 1.176,
            "profile_path": "/1rKagQ6kZnEWaa8CJaoWTLQUkBh.jpg",
            "credit_id": "5febb99e64f716003e102b18",
            "department": "Art",
            "job": "Production Design"
        },
        {
            "adult": false,
            "gender": 1,
            "id": 8864,
            "known_for_department": "Production",
            "name": "Karen Rea",
            "original_name": "Karen Rea",
            "popularity": 1.052,
            "profile_path": null,
            "credit_id": "5febb98fa14e10003b1aed82",
            "department": "Production",
            "job": "Casting"
        },
        {
            "adult": false,
            "gender": 2,
            "id": 11166,
            "known_for_department": "Sound",
            "name": "William Ross",
            "original_name": "William Ross",
            "popularity": 1.38,
            "profile_path": null,
            "credit_id": "5febb978945d36003e058332",
            "department": "Sound",
            "job": "Original Music Composer"
        },
        {
            "adult": false,
            "gender": 2,
            "id": 11506,
            "known_for_department": "Camera",
            "name": "Julio Macat",
            "original_name": "Julio Macat",
            "popularity": 1.646,
            "profile_path": null,
            "credit_id": "5febb9812d3721003ec76a28",
            "department": "Camera",
            "job": "Director of Photography"
        },
        {
            "adult": false,
            "gender": 0,
            "id": 14764,
            "known_for_department": "Sound",
            "name": "Christopher Assells",
            "original_name": "Christopher Assells",
            "popularity": 1.405,
            "profile_path": null,
            "credit_id": "5febba58c04429003fd864a3",
            "department": "Sound",
            "job": "Sound Editor"
        },
        {
            "adult": false,
            "gender": 2,
            "id": 18268,
            "known_for_department": "Writing",
            "name": "Peter Tolan",
            "original_name": "Peter Tolan",
            "popularity": 2.995,
            "profile_path": "/4FQITJL8furXIQJrKNJEQCiIK6J.jpg",
            "credit_id": "52fe47489251416c75093c89",
            "department": "Writing",
            "job": "Screenplay"
        },
        {
            "adult": false,
            "gender": 2,
            "id": 35498,
            "known_for_department": "Production",
            "name": "Craig Zadan",
            "original_name": "Craig Zadan",
            "popularity": 1.293,
            "profile_path": "/d9CIqpxKuXMMtceFX19ujMVpYpn.jpg",
            "credit_id": "5febb93fd40d4c003f86d841",
            "department": "Production",
            "job": "Executive Producer"
        },
        {
            "adult": false,
            "gender": 2,
            "id": 13426,
            "known_for_department": "Directing",
            "name": "Peter Segal",
            "original_name": "Peter Segal",
            "popularity": 4.926,
            "profile_path": "/x0nAuktiPai0OovveeegPAi0dRF.jpg",
            "credit_id": "52fe47479251416c75093c47",
            "department": "Directing",
            "job": "Director"
        },
        {
            "adult": false,
            "gender": 0,
            "id": 22009,
            "known_for_department": "Art",
            "name": "Michael Rizzo",
            "original_name": "Michael Rizzo",
            "popularity": 0.84,
            "profile_path": null,
            "credit_id": "5febb9e11d1bf4003d12d4e3",
            "department": "Art",
            "job": "Art Direction"
        },
        {
            "adult": false,
            "gender": 2,
            "id": 23352,
            "known_for_department": "Costume & Make-Up",
            "name": "Steve LaPorte",
            "original_name": "Steve LaPorte",
            "popularity": 1.38,
            "profile_path": null,
            "credit_id": "5febba12d40d4c003e865448",
            "department": "Costume & Make-Up",
            "job": "Makeup Department Head"
        },
        {
            "adult": false,
            "gender": 1,
            "id": 29019,
            "known_for_department": "Art",
            "name": "Gae S. Buckley",
            "original_name": "Gae S. Buckley",
            "popularity": 1.08,
            "profile_path": null,
            "credit_id": "5febb9a81511aa003ff4984b",
            "department": "Art",
            "job": "Art Direction"
        },
        {
            "adult": false,
            "gender": 1,
            "id": 11376,
            "known_for_department": "Costume & Make-Up",
            "name": "Betsy Cox",
            "original_name": "Betsy Cox",
            "popularity": 1.22,
            "profile_path": null,
            "credit_id": "5febb9f7cc277c0040071442",
            "department": "Costume & Make-Up",
            "job": "Costume Design"
        },
        {
            "adult": false,
            "gender": 2,
            "id": 46942,
            "known_for_department": "Editing",
            "name": "William Kerr",
            "original_name": "William Kerr",
            "popularity": 0.84,
            "profile_path": null,
            "credit_id": "5febb988761421003d898679",
            "department": "Editing",
            "job": "Editor"
        },
        {
            "adult": false,
            "gender": 2,
            "id": 52597,
            "known_for_department": "Production",
            "name": "Neil Meron",
            "original_name": "Neil Meron",
            "popularity": 1.025,
            "profile_path": "/wEHSJRkQaI7EEMBudbLcAqlrK9J.jpg",
            "credit_id": "5febb937945d36003d05abb0",
            "department": "Production",
            "job": "Executive Producer"
        },
        {
            "adult": false,
            "gender": 2,
            "id": 65711,
            "known_for_department": "Art",
            "name": "Gary Fettis",
            "original_name": "Gary Fettis",
            "popularity": 0.842,
            "profile_path": null,
            "credit_id": "5febb9ec07a808003f9286fc",
            "department": "Art",
            "job": "Set Decoration"
        },
        {
            "adult": false,
            "gender": 1,
            "id": 71423,
            "known_for_department": "Production",
            "name": "Tracy Barone",
            "original_name": "Tracy Barone",
            "popularity": 0.6,
            "profile_path": null,
            "credit_id": "5febb92da14e10003c18cb99",
            "department": "Production",
            "job": "Executive Producer"
        },
        {
            "adult": false,
            "gender": 2,
            "id": 71079,
            "known_for_department": "Production",
            "name": "Michael Ewing",
            "original_name": "Michael Ewing",
            "popularity": 1.943,
            "profile_path": null,
            "credit_id": "5febb94da14e10003b1aed65",
            "department": "Production",
            "job": "Co-Producer"
        },
        {
            "adult": false,
            "gender": 2,
            "id": 80824,
            "known_for_department": "Sound",
            "name": "Jay Nierenberg",
            "original_name": "Jay Nierenberg",
            "popularity": 0.972,
            "profile_path": null,
            "credit_id": "5febba998c22c0003d14308a",
            "department": "Sound",
            "job": "Supervising Sound Editor"
        },
        {
            "adult": false,
            "gender": 0,
            "id": 160243,
            "known_for_department": "Writing",
            "name": "E. Jack Kaplan",
            "original_name": "E. Jack Kaplan",
            "popularity": 1.001,
            "profile_path": null,
            "credit_id": "52fe47489251416c75093c71",
            "department": "Writing",
            "job": "Screenplay"
        },
        {
            "adult": false,
            "gender": 0,
            "id": 160243,
            "known_for_department": "Writing",
            "name": "E. Jack Kaplan",
            "original_name": "E. Jack Kaplan",
            "popularity": 1.001,
            "profile_path": null,
            "credit_id": "52fe47489251416c75093c77",
            "department": "Writing",
            "job": "Story"
        },
        {
            "adult": false,
            "gender": 0,
            "id": 192727,
            "known_for_department": "Writing",
            "name": "Richard Chapman",
            "original_name": "Richard Chapman",
            "popularity": 0.84,
            "profile_path": null,
            "credit_id": "52fe47489251416c75093c7d",
            "department": "Writing",
            "job": "Screenplay"
        },
        {
            "adult": false,
            "gender": 0,
            "id": 192727,
            "known_for_department": "Writing",
            "name": "Richard Chapman",
            "original_name": "Richard Chapman",
            "popularity": 0.84,
            "profile_path": null,
            "credit_id": "52fe47489251416c75093c83",
            "department": "Writing",
            "job": "Story"
        },
        {
            "adult": false,
            "gender": 0,
            "id": 1237509,
            "known_for_department": "Production",
            "name": "Jean Higgins",
            "original_name": "Jean Higgins",
            "popularity": 0.6,
            "profile_path": null,
            "credit_id": "5febb957d7107e003f278ad6",
            "department": "Production",
            "job": "Co-Producer"
        },
        {
            "adult": false,
            "gender": 0,
            "id": 1334172,
            "known_for_department": "Costume & Make-Up",
            "name": "Linda Kamp",
            "original_name": "Linda Kamp",
            "popularity": 0.631,
            "profile_path": null,
            "credit_id": "5febba00a14e10003e1a183d",
            "department": "Costume & Make-Up",
            "job": "Makeup Artist"
        },
        {
            "adult": false,
            "gender": 0,
            "id": 1391565,
            "known_for_department": "Art",
            "name": "Mick Cukurs",
            "original_name": "Mick Cukurs",
            "popularity": 0.6,
            "profile_path": null,
            "credit_id": "5febba4bd40d4c003f86da4a",
            "department": "Art",
            "job": "Set Designer"
        },
        {
            "adult": false,
            "gender": 1,
            "id": 1402153,
            "known_for_department": "Sound",
            "name": "Cathie Speakman",
            "original_name": "Cathie Speakman",
            "popularity": 1.286,
            "profile_path": null,
            "credit_id": "5febbaafb42242003d408cbd",
            "department": "Sound",
            "job": "Sound Editor"
        },
        {
            "adult": false,
            "gender": 0,
            "id": 1407354,
            "known_for_department": "Sound",
            "name": "Terry Rodman",
            "original_name": "Terry Rodman",
            "popularity": 0.84,
            "profile_path": null,
            "credit_id": "5febbaa35ff34e003efdee45",
            "department": "Sound",
            "job": "Supervising Sound Editor"
        },
        {
            "adult": false,
            "gender": 0,
            "id": 1407878,
            "known_for_department": "Sound",
            "name": "Steve Mann",
            "original_name": "Steve Mann",
            "popularity": 0.652,
            "profile_path": null,
            "credit_id": "5febba84d40d4c003f86db06",
            "department": "Sound",
            "job": "Sound Effects Editor"
        },
        {
            "adult": false,
            "gender": 2,
            "id": 1412228,
            "known_for_department": "Sound",
            "name": "Steve Nelson",
            "original_name": "Steve Nelson",
            "popularity": 1.26,
            "profile_path": null,
            "credit_id": "60d69a78c8a2d4002a3d6de8",
            "department": "Sound",
            "job": "Sound Effects Editor"
        },
        {
            "adult": false,
            "gender": 0,
            "id": 1419089,
            "known_for_department": "Production",
            "name": "Russ Kavanaugh",
            "original_name": "Russ Kavanaugh",
            "popularity": 1.214,
            "profile_path": null,
            "credit_id": "5febb96307a808003d909c7d",
            "department": "Production",
            "job": "Associate Producer"
        },
        {
            "adult": false,
            "gender": 2,
            "id": 1428855,
            "known_for_department": "Sound",
            "name": "Richard E. Yawn",
            "original_name": "Richard E. Yawn",
            "popularity": 1.4,
            "profile_path": null,
            "credit_id": "5febbabd5ad76b003acc023a",
            "department": "Sound",
            "job": "Sound Editor"
        },
        {
            "adult": false,
            "gender": 0,
            "id": 1462668,
            "known_for_department": "Costume & Make-Up",
            "name": "Mark Landon",
            "original_name": "Mark Landon",
            "popularity": 0.6,
            "profile_path": null,
            "credit_id": "5febba08a5d849003de41cd7",
            "department": "Costume & Make-Up",
            "job": "Makeup Artist"
        },
        {
            "adult": false,
            "gender": 0,
            "id": 1536092,
            "known_for_department": "Costume & Make-Up",
            "name": "Peter Montagna",
            "original_name": "Peter Montagna",
            "popularity": 0.6,
            "profile_path": null,
            "credit_id": "5febba27a5d849003ee43e38",
            "department": "Costume & Make-Up",
            "job": "Assistant Makeup Artist"
        },
        {
            "adult": false,
            "gender": 0,
            "id": 1557612,
            "known_for_department": "Sound",
            "name": "Jeffree Bloomer",
            "original_name": "Jeffree Bloomer",
            "popularity": 0.6,
            "profile_path": null,
            "credit_id": "5febba6264f716003c10117d",
            "department": "Sound",
            "job": "Sound Recordist"
        },
        {
            "adult": false,
            "gender": 0,
            "id": 1725663,
            "known_for_department": "Costume & Make-Up",
            "name": "Wayne Massarelli",
            "original_name": "Wayne Massarelli",
            "popularity": 0.6,
            "profile_path": null,
            "credit_id": "5febba1b07a80800409345fc",
            "department": "Costume & Make-Up",
            "job": "Makeup Artist"
        },
        {
            "adult": false,
            "gender": 2,
            "id": 1748479,
            "known_for_department": "Sound",
            "name": "Steven Gerrior",
            "original_name": "Steven Gerrior",
            "popularity": 0.84,
            "profile_path": null,
            "credit_id": "5febba79761421003f89848d",
            "department": "Sound",
            "job": "Assistant Sound Editor"
        },
        {
            "adult": false,
            "gender": 0,
            "id": 1965918,
            "known_for_department": "Sound",
            "name": "Hank Garfield",
            "original_name": "Hank Garfield",
            "popularity": 0.919,
            "profile_path": null,
            "credit_id": "5febba6ab42242003e40a1cb",
            "department": "Sound",
            "job": "Sound"
        },
        {
            "adult": false,
            "gender": 2,
            "id": 1995913,
            "known_for_department": "Crew",
            "name": "Tony R. Medina",
            "original_name": "Tony R. Medina",
            "popularity": 1.595,
            "profile_path": null,
            "credit_id": "5aa5285ec3a3687c32021a3b",
            "department": "Crew",
            "job": "Propmaker"
        },
        {
            "adult": false,
            "gender": 0,
            "id": 2406818,
            "known_for_department": "Costume & Make-Up",
            "name": "Sara Seidman Vance",
            "original_name": "Sara Seidman Vance",
            "popularity": 0.6,
            "profile_path": null,
            "credit_id": "5febba30cc277c003d077793",
            "department": "Costume & Make-Up",
            "job": "Makeup Artist"
        },
        {
            "adult": false,
            "gender": 0,
            "id": 2916024,
            "known_for_department": "Art",
            "name": "Mike Austin",
            "original_name": "Mike Austin",
            "popularity": 0.6,
            "profile_path": null,
            "credit_id": "5febb9d8bf7744003e28b088",
            "department": "Art",
            "job": "Set Decoration"
        }
    ]
}